riskcontrol/LogisticScoreCard.py
riskcontrol/TwoFeatureHeatmap.py
riskcontrol/__init__.py
riskcontrol/compute_iv.py
riskcontrol/ks4score.py
riskcontrol-0.1.20.dist-info/LICENSE
riskcontrol-0.1.20.dist-info/METADATA
riskcontrol-0.1.20.dist-info/WHEEL
riskcontrol-0.1.20.dist-info/top_level.txt
riskcontrol-0.1.20.dist-info/RECORD
