Metadata-Version: 2.1
Name: riskcontrol
Version: 0.1.20
Summary: risk control modeling
Home-page: UNKNOWN
Author: SimaShanhe
Author-email: hsliu_em@126.com
License: UNKNOWN
Platform: UNKNOWN
Classifier: Programming Language :: Python :: 3
Classifier: License :: OSI Approved :: MIT License
Classifier: Operating System :: OS Independent
Requires-Dist: scikit-learn (>=0.21.3)
Requires-Dist: scipy
Requires-Dist: numpy
Requires-Dist: matplotlib
Requires-Dist: seaborn
Requires-Dist: prettytable
Requires-Dist: tqdm
